restore-mtime/__init__.py
restore-mtime/restore-mtime.py
restore-mtime/restore_mtime.py
restore_mtime/__init__.py
restore_mtime/restore_mtime.py
restore_mtime-0.1.1.dist-info/LICENSE.txt
restore_mtime-0.1.1.dist-info/METADATA
restore_mtime-0.1.1.dist-info/WHEEL
restore_mtime-0.1.1.dist-info/entry_points.txt
restore_mtime-0.1.1.dist-info/top_level.txt
restore_mtime-0.1.1.dist-info/RECORD
