Metadata-Version: 2.1
Name: restore-mtime
Version: 0.1.1
Summary: Command line utility for resotration of modification time (mtime) of files from tar archive into filesystem if the content matches
Home-page: https://github.com/eerorika/restore-mtime
Author: Eero Rikalainen
Author-email: eerorika@gmail.com
License: MIT
Platform: UNKNOWN
